hpa/__init__.py
hpa/_app.py
hpa/_http.py
hpa/_message_serializer.py
hpa/_messages.py
hpa/messaging.py
hpa-1.0.0.dist-info/METADATA
hpa-1.0.0.dist-info/WHEEL
hpa-1.0.0.dist-info/top_level.txt
hpa-1.0.0.dist-info/RECORD
